{"type":"FeatureCollection","name":"Surabaya","crs":{"type":"name","properties":{"name":"urn:ogc:def:crs:OGC:1.3:CRS84"}},"features":[{"type":"Feature","properties":{"Id":1,"Kabupaten":"Kota Denpasar","Kecamatan":"Denpasar Selatan"},"geometry":{"coordinates":[112.7386062284171,-7.272831322566162],"type":"Point"}},{"type":"Feature","properties":{},"geometry":{"coordinates":[112.75406851214524,-7.265303920747456],"type":"Point"}},{"type":"Feature","properties":{},"geometry":{"coordinates":[112.74867557093347,-7.2798896130605755],"type":"Point"}}]}